myfitnesspal/__init__.py
myfitnesspal/base.py
myfitnesspal/client.py
myfitnesspal/cmdline.py
myfitnesspal/commands.py
myfitnesspal/day.py
myfitnesspal/entry.py
myfitnesspal/exceptions.py
myfitnesspal/exercise.py
myfitnesspal/fooditem.py
myfitnesspal/fooditemserving.py
myfitnesspal/keyring_utils.py
myfitnesspal/meal.py
myfitnesspal/note.py
myfitnesspal/types.py
tests/__init__.py
tests/base.py
tests/test_client.py
tests/test_integration.py
myfitnesspal-2.1.0.dist-info/LICENSE
myfitnesspal-2.1.0.dist-info/METADATA
myfitnesspal-2.1.0.dist-info/WHEEL
myfitnesspal-2.1.0.dist-info/entry_points.txt
myfitnesspal-2.1.0.dist-info/top_level.txt
myfitnesspal-2.1.0.dist-info/RECORD
