Metadata-Version: 2.1
Name: myfitnesspal
Version: 2.1.0
Summary: Access health and fitness data stored in Myfitnesspal
Home-page: http://github.com/coddingtonbear/python-myfitnesspal/
Author: Adam Coddington
Author-email: me@adamcoddington.net
Classifier: Intended Audience :: Developers
Classifier: License :: OSI Approved :: MIT License
Classifier: Operating System :: OS Independent
Classifier: Programming Language :: Python
Classifier: Topic :: Utilities
License-File: LICENSE
